README.rst
setup.py
calyx/VarScan.v2.3.9.jar
calyx/__init__.py
calyx/calyx
calyx/example.input.tab
calyx.egg-info/PKG-INFO
calyx.egg-info/SOURCES.txt
calyx.egg-info/dependency_links.txt
calyx.egg-info/top_level.txt