Metadata-Version: 1.1
Name: calyx
Version: 1.0
Summary: calyx
Home-page: www.calyx.biz
Author: Yingxiang Li
Author-email: xlccalyx@gmail.com
License: GPLv3
Download-URL: http://www.calyx.biz/downloading--1997936733.html
Keywords: calyx
Platform: UNKNOWN
Classifier: Development Status :: 3 - Alpha
Classifier: Intended Audience :: Developers
Classifier: Topic :: Software Development :: Build Tools
Classifier: License :: OSI Approved :: GNU General Public License v3 (GPLv3)
Classifier: Programming Language :: Python :: 2.7
